[
  {
    "code": "KALI-STARTER-3USER",
    "plan": "Starter",
    "status": "Available",
    "pricePerUser": 23000,
    "userLimit": 3,
    "billingCycle": "monthly",
    "monthlyAmount": 69000,
    "validUntil": "2026-06-18"
  },
  {
    "code": "KALI-BUSINESS-7USER",
    "plan": "Business",
    "status": "Available",
    "pricePerUser": 75000,
    "userLimit": 7,
    "billingCycle": "monthly",
    "monthlyAmount": 525000,
    "validUntil": "2026-06-18"
  },
  {
    "code": "KALI-LIFETIME-5USER",
    "plan": "Lifetime",
    "status": "Available",
    "pricePerUser": 0,
    "userLimit": 5,
    "billingCycle": "lifetime",
    "monthlyAmount": 0,
    "oneTimePrice": 1500000,
    "validUntil": "2099-12-31"
  }
]